main.py
setup.py
sampling_util.egg-info/PKG-INFO
sampling_util.egg-info/SOURCES.txt
sampling_util.egg-info/dependency_links.txt
sampling_util.egg-info/requires.txt
sampling_util.egg-info/top_level.txt