Metadata-Version: 2.1
Name: sampling_util
Version: 9.6
Summary: anon
Author: anon
Author-email: xxx@outlook.com
Requires-Dist: requests
Requires-Dist: psutil
